clodss/__init__.py
clodss/clodss.py
clodss/common.py
clodss/hashmaps.py
clodss/keys.py
clodss/lists.py
clodss/router.py
tests/__init__.py
tests/test_hashmaps.py
tests/test_keys.py
tests/test_lists.py
clodss-0.0.6.dist-info/COPYING
clodss-0.0.6.dist-info/METADATA
clodss-0.0.6.dist-info/WHEEL
clodss-0.0.6.dist-info/top_level.txt
clodss-0.0.6.dist-info/RECORD
