Metadata-Version: 2.1
Name: clodss
Version: 0.0.6
Summary: On-Disk data-structures store with redis-like API.
Home-page: https://github.com/codomatech/clodss
Author: Codoma.tech Team
Author-email: info@codoma.tech
License: UNKNOWN
Platform: UNKNOWN
Classifier: Programming Language :: Python :: 3
Classifier: License :: OSI Approved :: BSD License
Classifier: Operating System :: OS Independent
Requires-Python: >=3.6
Requires-Dist: lsm-db
